LICENSE
MANIFEST.in
README.md
setup.cfg
setup.py
inputao/__init__.py
inputao/core.py
inputao/stdinput.py
inputao.egg-info/PKG-INFO
inputao.egg-info/SOURCES.txt
inputao.egg-info/dependency_links.txt
inputao.egg-info/top_level.txt
inputao.egg-info/zip-safe