Metadata-Version: 2.1
Name: inputao
Version: 1.2
Summary: Um input melhor para ajudar os iniciantes em Python.
Home-page: http://github.com/henriquebastos/inputao/
Author: Henrique Bastos
Author-email: henrique@bastos.net
License: MIT
Keywords: input,beginner,tool
Platform: any
Classifier: Development Status :: 5 - Production/Stable
Classifier: Intended Audience :: Developers
Classifier: License :: OSI Approved :: MIT License
Classifier: Natural Language :: Portuguese
Classifier: Operating System :: OS Independent
Classifier: Programming Language :: Python
Classifier: Programming Language :: Python :: 3
Classifier: Programming Language :: Python :: 2
Classifier: Topic :: Software Development :: Libraries
